random_events_lib.cpython-311-x86_64-linux-gnu.so
random-events-lib/__init__.py
random-events-lib/setup.py
random-events-lib/doc/conf.py
random-events-lib/export/bindings.cpp
random-events-lib/export/python_binding_example.py
random-events-lib/random_events_lib/src/product_algebra.cpp
random-events-lib/random_events_lib/src/set.cpp
random-events-lib/random_events_lib/src/sigma_algebra.cpp
random_events/__init__.py
random_events/interval.py
random_events/polytope.py
random_events/product_algebra.py
random_events/set.py
random_events/sigma_algebra.py
random_events/utils.py
random_events/variable.py
random_events-4.1.18.dist-info/METADATA
random_events-4.1.18.dist-info/WHEEL
random_events-4.1.18.dist-info/top_level.txt
random_events-4.1.18.dist-info/RECORD
