Metadata-Version: 2.4
Name: random_events
Version: 4.1.18
Summary: Random random events for probabilistic reasoning
Home-page: https://github.com/tomsch420/random-events
Author: Tom Schierenbeck
Author-email: Tom Schierenbeck <tom_sch@uni-bremen.de>
License: MIT License
Project-URL: Homepage, https://github.com/tomsch420/random-events
Project-URL: Download, https://github.com/tomsch420/random-events
Project-URL: Bug Tracker, https://github.com/tomsch420/random-events/issues
Keywords: random events,probabilistic machine learning,probability theory,variables,reasoning under uncertainty
Classifier: Programming Language :: Python :: 3
Classifier: License :: OSI Approved :: MIT License
Classifier: Operating System :: OS Independent
Requires-Python: >=3.8
Requires-Dist: setuptools
Requires-Dist: pybind11
Dynamic: author
Dynamic: home-page
Dynamic: requires-python
